trust_eval/__init__.py
trust_eval/auto_ais_loader.py
trust_eval/config.py
trust_eval/data.py
trust_eval/evaluator.py
trust_eval/llm.py
trust_eval/logging_config.py
trust_eval/metrics.py
trust_eval/post_hoc_cite.py
trust_eval/response_generator.py
trust_eval/retrieval.py
trust_eval/searcher.py
trust_eval/utils.py
trust_eval-0.1.3.dist-info/METADATA
trust_eval-0.1.3.dist-info/WHEEL
trust_eval-0.1.3.dist-info/RECORD
