Metadata-Version: 2.1
Name: trust_eval
Version: 0.1.3
Summary: Metric to measure RAG responses with inline citations
Home-page: https://github.com/shanghongsim/trust-eval
License: CC BY-NC 4.0
Keywords: RAG,evaluation,metrics,citation
Author: Shang Hong Sim
Author-email: simshanghong@gmail.com
Requires-Python: >=3.10,<3.12
Classifier: License :: Other/Proprietary License
Classifier: Programming Language :: Python :: 3
Classifier: Programming Language :: Python :: 3.10
Classifier: Programming Language :: Python :: 3.11
Requires-Dist: colorlog (>=6.9.0,<7.0.0)
Requires-Dist: fuzzywuzzy (>=0.18.0,<0.19.0)
Requires-Dist: nltk (>=3.9.1,<4.0.0)
Requires-Dist: peft (>=0.14.0,<0.15.0)
Requires-Dist: py3nvml (>=0.2.7,<0.3.0)
Requires-Dist: python-levenshtein (>=0.26.1,<0.27.0)
Requires-Dist: scipy (>=1.14.1,<2.0.0)
Requires-Dist: sentence-transformers (>=3.4.0,<4.0.0)
Requires-Dist: vllm (>=0.6.6.post1,<0.7.0)
Project-URL: Repository, https://github.com/shanghongsim/trust-eval
